LICENSE
pylink_utils/__init__.py
pylink_utils/aws_utils/__init__.py
pylink_utils/aws_utils/postgresql_db_connection.py
pylink_utils/aws_utils/secret_handler.py
pylink_utils/aws_utils/session_abc.py
pylink_utils/data_tools/__init__.py
pylink_utils/data_tools/html_to_json.py
pylink_utils-1.2.4.dist-info/LICENSE
pylink_utils-1.2.4.dist-info/WHEEL
pylink_utils-1.2.4.dist-info/METADATA
pylink_utils-1.2.4.dist-info/RECORD
