Metadata-Version: 2.1
Name: pylink-utils
Version: 1.2.4
Summary: 
Home-page: https://github.com/Pylink-Analytics/pylink_utils
License: MIT
Author: douglas-peter
Author-email: 76939369+douglas-peter@users.noreply.github.com
Requires-Python: >=3.8,<3.11
Classifier: License :: OSI Approved :: MIT License
Classifier: Programming Language :: Python :: 3
Classifier: Programming Language :: Python :: 3.10
Classifier: Programming Language :: Python :: 3.8
Classifier: Programming Language :: Python :: 3.9
Requires-Dist: awswrangler (>=2.16.1,<3.0.0)
Requires-Dist: boto3 (>=1.24.46,<2.0.0)
Requires-Dist: botocore (>=1.27.46,<2.0.0)
Requires-Dist: bs4 (==0.0.1)
Requires-Dist: lxml (==4.8.0)
Requires-Dist: pandas (>=1.4.3,<2.0.0)
Project-URL: Repository, https://github.com/Pylink-Analytics/pylink_utils
